{
  "flightsets": [
    {
      "id": 1,
      "name": "New Flight Set 1",
      "description": "Nulla vitae elit libero",
      "reference_id": null,
      "is_template": false,
      "flights": [
          {
            "id": 1,
            "start_date": "2017-03-21T02:33:51.607Z",
            "end_date": "2017-04-21T02:33:51.607Z",
            "budget_amount": 10000,
            "budget_type": "USD"
          },
          {
            "id": 2,
            "start_date": "2017-05-21T02:33:51.607Z" ,
            "end_date": "2017-06-21T02:33:51.607Z",
            "budget_amount": 20000,
            "budget_type": "USD"
        }
      ],
      "budget_type": "USD",
      "audit": {
          "created": {
              "by": {
                  "id": 1,
                  "first_name": "Kris",
                  "last_name": "Dunn",
                  "email": "kris.dunn@bulls.com"
              },
              "at": "2018-03-21T02:33:51.607Z"
          },
          "updated": {
              "by": {
                  "id": 1,
                  "first_name": "Kris",
                  "last_name": "Dunn",
                  "email": "kris.dunn@bulls.com"
              },
              "at": "2018-03-21T02:33:51.607Z"
          }
      }
    },
    {
      "id": 2,
      "name": "New Flight Set 2",
      "description": "Nulla vitae elit libero, a pharetra augue. Fusce dapibus, tellus ac cursus commodo, tortor mauris condimentum nibh, ut fermentum massa justo sit amet risus.",
      "reference_id": null,
      "is_template": false,
      "flights": [
          {
            "id": 1,
            "start_date": "2017-05-21T02:33:51.607Z",
            "end_date": "2017-07-21T02:33:51.607Z",
            "budget_amount": 500,
            "budget_type": "GRP"
          },
          {
            "id": 2,
            "start_date": "2017-08-21T02:33:51.607Z",
            "end_date": "2017-09-21T02:33:51.607Z",
            "budget_amount": 1000,
            "budget_type": "GRP"
          }
      ],
      "budget_type": "GRP",
      "audit": {
          "created": {
              "by": {
                  "id": 1,
                  "first_name": "Lauri",
                  "last_name": "Markannen",
                  "email": "lauri@bulls.com"
              },
              "at": "2018-05-21T02:33:51.607Z"
          },
          "updated": {
              "by": {
                  "id": 1,
                  "first_name": "Lauri",
                  "last_name": "Markannen",
                  "email": "lauri@bulls.com"
              },
              "at": "2018-05-21T02:33:51.607Z"
          }
      }
    }
  ],
  "segments": [{"name":"F_2_5", "type":"Demographic", "provider":"Nielsen", "size": 7620000, "isUniversal":true, "genderCode": "F", "minAge": 2, "maxAge":5},
    {"name":"F_6_8", "type":"Demographic", "provider":"Nielsen", "size": 5730000, "isUniversal":true, "genderCode": "F", "minAge": 6, "maxAge": 8},
    {"name":"F_9_11", "type":"Demographic", "provider":"Nielsen", "size": 5930000, "isUniversal":true, "genderCode": "F", "minAge": 9, "maxAge":11},
    {"name":"F_12_14", "type":"Demographic", "provider":"Nielsen", "size": 5940000, "isUniversal":true, "genderCode": "F", "minAge": 12, "maxAge":14},
    {"name":"F_15_17", "type":"Demographic", "provider":"Nielsen", "size": 6030000, "isUniversal":true, "genderCode": "F", "minAge": 15, "maxAge":17},
    {"name":"F_18_20", "type":"Demographic", "provider":"Nielsen", "size": 6340000, "isUniversal":true, "genderCode": "F", "minAge": 18, "maxAge":20},
    {"name":"F_21_24", "type":"Demographic", "provider":"Nielsen", "size": 8010000, "isUniversal":true, "genderCode": "F", "minAge": 21, "maxAge":24},
    {"name":"F_25_29", "type":"Demographic", "provider":"Nielsen", "size": 10000000, "isUniversal":true, "genderCode": "F", "minAge": 25, "maxAge":29},
    {"name":"F_30_34", "type":"Demographic", "provider":"Nielsen", "size": 10210000, "isUniversal":true, "genderCode": "F", "minAge": 30, "maxAge":34},
    {"name":"F_35_39", "type":"Demographic", "provider":"Nielsen", "size": 9960000, "isUniversal":true, "genderCode": "F", "minAge": 35, "maxAge":39},
    {"name":"F_40_44", "type":"Demographic", "provider":"Nielsen", "size": 9900000, "isUniversal":true, "genderCode": "F", "minAge": 40, "maxAge":44},
    {"name":"F_45_49", "type":"Demographic", "provider":"Nielsen", "size": 10210000, "isUniversal":true, "genderCode": "F", "minAge": 45, "maxAge":49},
    {"name":"F_50_54", "type":"Demographic", "provider":"Nielsen", "size": 10710000, "isUniversal":true, "genderCode": "F", "minAge": 50, "maxAge":54},
    {"name":"F_55_64", "type":"Demographic", "provider":"Nielsen", "size": 21070000, "isUniversal":true, "genderCode": "F", "minAge": 55, "maxAge":64},
    {"name":"F_65_999", "type":"Demographic", "provider":"Nielsen", "size": 26660000, "isUniversal":true, "genderCode": "F", "minAge": 65, "maxAge":999},
    {"name":"M_2_5", "type":"Demographic", "provider":"Nielsen", "size": 7960000, "isUniversal":true, "genderCode": "M", "minAge": 2, "maxAge":5},
    {"name":"M_6_8", "type":"Demographic", "provider":"Nielsen", "size": 5980000, "isUniversal":true, "genderCode": "M", "minAge": 6, "maxAge":8},
    {"name":"M_9_11", "type":"Demographic", "provider":"Nielsen", "size": 6190000, "isUniversal":true, "genderCode": "M", "minAge": 9, "maxAge":11},
    {"name":"M_12_14", "type":"Demographic", "provider":"Nielsen", "size": 6190000, "isUniversal":true, "genderCode": "M", "minAge": 12, "maxAge":14},
    {"name":"M_15_17", "type":"Demographic", "provider":"Nielsen", "size": 6260000, "isUniversal":true, "genderCode": "M", "minAge": 15,"maxAge": 17},
    {"name":"M_18_20", "type":"Demographic", "provider":"Nielsen", "size": 6490000, "isUniversal":true, "genderCode": "M", "minAge": 18, "maxAge":20},
    {"name":"M_21_24", "type":"Demographic", "provider":"Nielsen", "size": 8190000, "isUniversal":true, "genderCode": "M", "minAge": 21, "maxAge":24},
    {"name":"M_25_29", "type":"Demographic", "provider":"Nielsen", "size": 9990000, "isUniversal":true, "genderCode": "M", "minAge": 25, "maxAge":29},
    {"name":"M_30_34", "type":"Demographic", "provider":"Nielsen", "size": 10060000, "isUniversal":true, "genderCode": "M", "minAge": 30, "maxAge":34},
    {"name":"M_35_39", "type":"Demographic", "provider":"Nielsen", "size": 9660000, "isUniversal":true, "genderCode": "M", "minAge": 35, "maxAge":39},
    {"name":"M_40_44", "type":"Demographic", "provider":"Nielsen", "size": 9530000, "isUniversal":true, "genderCode": "M", "minAge": 40, "maxAge":44},
    {"name":"M_45_49", "type":"Demographic", "provider":"Nielsen", "size": 9770000, "isUniversal":true, "genderCode": "M", "minAge": 45, "maxAge":49},
    {"name":"M_50_54", "type":"Demographic", "provider":"Nielsen", "size": 10170000, "isUniversal":true, "genderCode": "M", "minAge": 50, "maxAge":54},
    {"name":"M_55_64", "type":"Demographic", "provider":"Nielsen", "size": 19450000, "isUniversal":true, "genderCode": "M", "minAge": 55, "maxAge":64},
    {"name":"M_65_999", "type":"Demographic", "provider":"Nielsen", "size": 21460000, "isUniversal":true, "genderCode": "M", "minAge": 65, "maxAge":999}
  ],
  "content_constraint_sets": [
    {
        "name": "Constraint 1",
        "description": "Nulla vitae elit libero, a pharetra augue. Fusce dapibus, tellus ac cursus commodo, tortor mauris condimentum nibh, ut fermentum massa justo sit amet risus.",
        "constraints": [
            {
                "type": "Include, Exclude",
                "media_groups": {
                    "items": [1, 2]
                },
                "nielsen_networks": {
                    "items": [3, 4]
                },
                "nielsen_programs": {
                    "items": [6, 7, 8]
                }
            }
        ]
    },
    {
        "name": "Constraint 2",
        "description": "Another description here",
        "constraints": [
            {
                "type": "Include, Exclude",
                "media_groups": {
                    "items": [1, 2]
                },
                "nielsen_networks": {
                    "items": [3, 4]
                },
                "nielsen_programs": {
                    "items": [6, 7, 8]
                }
            }
        ]
    }
  ],
  "constraints": {
        "media_group": [
            {"id": 0, "name": "first_media_group"},
            {"id": 1, "name": "second_media_group"},
            {"id": 2, "name": "third_media_group"},
            {"i3": 3, "name": "fourth_media_group"}
        ],
        "nielsen_network": [
            {"id": 0, "name": "firstniel_sen_network"},
            {"id": 1, "name": "second_nielsen_network"},
            {"id": 2, "name": "third_nielsen_network"},
            {"id": 3, "name": "fourth_nielsen_network"}
        ],
        "nielsen_program": [
            {"id": 0, "name": "firstniel_sen_program"},
            {"id": 1, "name": "second_nielsen_program"},
            {"id": 2, "name": "third_nielsen_program"},
            {"id": 3, "name": "fourth_nielsen_program"}
        ],
        "nielsen_category": [
            {"id": 0, "name": "firstniels_en_category"},
            {"id": 1, "name": "second_nielsen_category"},
            {"id": 2, "name": "third_nielsen_category"},
            {"id": 3, "name": "fourth_nielsen_category"}
        ],
        "nielsen_daypart": [
            {"id": 0, "name": "firstniel_sen_daypart"},
            {"id": 1, "name": "second_nielsen_daypart"},
            {"id": 2, "name": "third_nielsen_daypart"},
            {"id": 3, "name": "fourth_nielsen_daypart"}
        ],
        "day_of_week": [
            {"id": 0, "name": "first_day_of_week"},
            {"id": 1, "name": "second_day_of_week"},
            {"id": 2, "name": "third_day_of_week"},
            {"i3": 3, "name": "fourth_day_of_week"}
        ]
    }
}

